{
  "$generated": "AUTO-GENERATED from contracts/Sidebar.contract.json — DO NOT EDIT (pnpm codegen)",
  "name": "Sidebar",
  "component": "Sidebar",
  "version": "1.0.0",
  "level": "organism",
  "category": "Navigation",
  "status": "beta",
  "summary": "좌측 고정 내비게이션 — 브랜드 슬롯 + 섹션·잎·가지 목록. 라우팅을 모른다",
  "states": [
    "default",
    "hover",
    "focus-visible",
    "open",
    "selected"
  ],
  "variantProperties": {},
  "properties": [
    {
      "name": "Label",
      "type": "TEXT",
      "default": "",
      "prop": "label",
      "summary": "주 내비게이션 랜드마크의 접근 가능한 이름 — <nav aria-label> 에 그대로 들어간다"
    },
    {
      "name": "ActiveHref",
      "type": "TEXT",
      "default": "",
      "prop": "activeHref",
      "summary": "지금 켜져야 할 링크의 href"
    },
    {
      "name": "OpenId",
      "type": "TEXT",
      "default": "",
      "prop": "openId",
      "summary": "펼쳐진 가지의 id"
    },
    {
      "name": "Brand",
      "type": "TEXT",
      "default": "",
      "prop": "brand",
      "summary": "상단 브랜드 영역 슬롯 — 로고·워드마크가 들어온다"
    }
  ],
  "tokens": {
    "surface": "color.surface.default",
    "border": "color.border.default",
    "borderWidth": "border-width.thin",
    "widthUnit": "space.6",
    "brandHeightUnit": "space.6",
    "brandPadX": "space.5",
    "brandGap": "space.3",
    "navPadX": "space.3",
    "navPadY": "space.4",
    "sectionTitlePadX": "space.3",
    "sectionTitlePadY": "space.2",
    "sectionTitleText": "color.text.muted",
    "sectionTitleFontSize": "primitive.typography.font-size.12",
    "itemGap": "space.1",
    "itemInnerGap": "space.3",
    "itemPadX": "space.3",
    "itemPadY": "space.3",
    "itemText": "color.text.default",
    "itemTypography": "typography.label.md",
    "itemActiveText": "color.action.primary.default",
    "itemMarkerWidth": "border-width.medium",
    "itemHoverBackground": "color.surface.raised",
    "subItemPadY": "space.2",
    "subItemIndent": "space.6",
    "subItemText": "color.text.muted",
    "subItemTypography": "typography.label.md",
    "chevronText": "color.text.muted",
    "focusRing": "color.border.focus",
    "transitionDuration": "motion.duration.fast",
    "transitionEasing": "motion.easing.standard"
  },
  "anatomy": {
    "kind": "frame",
    "name": "Sidebar",
    "layout": "VERTICAL",
    "align": "MIN",
    "styles": {
      "fill": "surface",
      "stroke": "border",
      "strokeWidth": "borderWidth"
    },
    "children": [
      {
        "kind": "frame",
        "name": "Brand",
        "layout": "HORIZONTAL",
        "align": "CENTER",
        "styles": {
          "padX": "brandPadX",
          "gap": "brandGap",
          "stroke": "border",
          "strokeWidth": "borderWidth"
        },
        "children": [
          {
            "kind": "text",
            "name": "Wordmark",
            "text": "LOGO",
            "styles": {
              "color": "itemText",
              "typography": "itemTypography"
            }
          }
        ]
      },
      {
        "kind": "frame",
        "name": "Nav",
        "layout": "VERTICAL",
        "align": "MIN",
        "grow": true,
        "styles": {
          "padX": "navPadX",
          "padY": "navPadY",
          "gap": "itemGap"
        },
        "children": [
          {
            "kind": "text",
            "name": "SectionTitle",
            "text": "운영",
            "styles": {
              "color": "sectionTitleText",
              "fontSize": "sectionTitleFontSize",
              "typography": "itemTypography"
            }
          },
          {
            "kind": "frame",
            "name": "Item",
            "layout": "HORIZONTAL",
            "align": "CENTER",
            "repeat": 4,
            "styles": {
              "padX": "itemPadX",
              "padY": "itemPadY",
              "gap": "itemInnerGap"
            },
            "children": [
              {
                "kind": "vector",
                "name": "Icon",
                "svgIcon": "layout-grid",
                "svg": "<svg xmlns=\"http://www.w3.org/2000/svg\" viewBox=\"0 0 24 24\" fill=\"none\" stroke=\"#000000\" stroke-width=\"1.75\" stroke-linecap=\"round\" stroke-linejoin=\"round\"><rect x=\"3\" y=\"3\" width=\"7\" height=\"7\" rx=\"1.5\" /> <rect x=\"14\" y=\"3\" width=\"7\" height=\"7\" rx=\"1.5\" /> <rect x=\"3\" y=\"14\" width=\"7\" height=\"7\" rx=\"1.5\" /> <rect x=\"14\" y=\"14\" width=\"7\" height=\"7\" rx=\"1.5\" /></svg>"
              },
              {
                "kind": "text",
                "name": "Label",
                "text": "대시보드",
                "styles": {
                  "color": "itemText",
                  "typography": "itemTypography"
                },
                "samples": [
                  "대시보드",
                  "회원",
                  "콘텐츠",
                  "설정"
                ]
              }
            ]
          },
          {
            "kind": "frame",
            "name": "Branch",
            "layout": "HORIZONTAL",
            "align": "CENTER",
            "styles": {
              "padX": "itemPadX",
              "padY": "itemPadY",
              "gap": "itemInnerGap"
            },
            "children": [
              {
                "kind": "vector",
                "name": "BranchIcon",
                "svgIcon": "building",
                "svg": "<svg xmlns=\"http://www.w3.org/2000/svg\" viewBox=\"0 0 24 24\" fill=\"none\" stroke=\"#000000\" stroke-width=\"1.75\" stroke-linecap=\"round\" stroke-linejoin=\"round\"><path d=\"M4 21V5a2 2 0 0 1 2-2h8a2 2 0 0 1 2 2v16\" /> <path d=\"M16 9h2a2 2 0 0 1 2 2v10\" /> <path d=\"M2 21h20\" /> <path d=\"M8 7h4\" /> <path d=\"M8 11h4\" /> <path d=\"M8 15h4\" /></svg>"
              },
              {
                "kind": "text",
                "name": "BranchLabel",
                "text": "기업 정보",
                "grow": true,
                "styles": {
                  "color": "itemText",
                  "typography": "itemTypography"
                }
              },
              {
                "kind": "vector",
                "name": "Chevron",
                "svgIcon": "chevron-down",
                "svg": "<svg xmlns=\"http://www.w3.org/2000/svg\" viewBox=\"0 0 24 24\" fill=\"none\" stroke=\"#000000\" stroke-width=\"1.75\" stroke-linecap=\"round\" stroke-linejoin=\"round\"><path d=\"m6 9 6 6 6-6\" /></svg>"
              }
            ]
          },
          {
            "kind": "frame",
            "name": "SubItem",
            "layout": "HORIZONTAL",
            "align": "MIN",
            "repeat": 3,
            "styles": {
              "padX": "subItemIndent",
              "padY": "subItemPadY"
            },
            "children": [
              {
                "kind": "text",
                "name": "SubLabel",
                "text": "회사 소개",
                "styles": {
                  "color": "subItemText",
                  "typography": "subItemTypography"
                },
                "samples": [
                  "회사 소개",
                  "연혁",
                  "인증서"
                ]
              }
            ]
          }
        ]
      }
    ]
  }
}
